pyDICI/__init__.py
pyDICI-0.0.6.dist-info/LICENSE
pyDICI-0.0.6.dist-info/METADATA
pyDICI-0.0.6.dist-info/WHEEL
pyDICI-0.0.6.dist-info/top_level.txt
pyDICI-0.0.6.dist-info/RECORD
