Metadata-Version: 2.1
Name: pyDICI
Version: 0.0.6
Summary: Pacote para enviar dados ao DICI
Home-page: https://github.com/danielsioli/DICI
Author: Daniel Oliveira
Author-email: danielsioli@gmail.com
License: Creative Commons Attribution-Noncommercial-Share Alike license
Keywords: anatel,dici
Platform: UNKNOWN
Classifier: Development Status :: 4 - Beta
Classifier: Intended Audience :: Developers
Classifier: Topic :: Internet :: WWW/HTTP
Classifier: Programming Language :: Python :: 3
Classifier: Programming Language :: Python :: 3.3
Classifier: Programming Language :: Python :: 3.4
Classifier: Programming Language :: Python :: 3.5
Requires-Dist: selenium
Requires-Dist: datetime
Requires-Dist: argparse
Requires-Dist: pandas
Requires-Dist: termcolor
Requires-Dist: xlrd
